setup.py
cricscore/__init__.py
cricscore.egg-info/PKG-INFO
cricscore.egg-info/SOURCES.txt
cricscore.egg-info/dependency_links.txt
cricscore.egg-info/not-zip-safe
cricscore.egg-info/top_level.txt