Metadata-Version: 1.0
Name: cricscore
Version: 0.1
Summary: Live cricket scores
Home-page: http://github.com/titunian/cricscore
Author: Titunian
Author-email: titunian@gmail.com
License: MIT
Platform: UNKNOWN
